winzy_weather/__init__.py
winzy_weather-0.0.1.dist-info/LICENSE
winzy_weather-0.0.1.dist-info/METADATA
winzy_weather-0.0.1.dist-info/WHEEL
winzy_weather-0.0.1.dist-info/entry_points.txt
winzy_weather-0.0.1.dist-info/top_level.txt
winzy_weather-0.0.1.dist-info/RECORD
