Metadata-Version: 2.1
Name: winzy-weather
Version: 0.0.1
Summary: Weather using the excellent wttr.in
Author: Sukhbinder Singh
License: Apache-2.0
Project-URL: Homepage, https://github.com/sukhbinder/winzy-weather
Project-URL: Changelog, https://github.com/sukhbinder/winzy-weather/releases
Project-URL: Issues, https://github.com/sukhbinder/winzy-weather/issues
Project-URL: CI, https://github.com/sukhbinder/winzy-weather/actions
Classifier: License :: OSI Approved :: Apache Software License
License-File: LICENSE
Requires-Dist: winzy
Provides-Extra: test
Requires-Dist: pytest; extra == "test"
